tendermint_chunked_genesis_download/__init__.py
tendermint_chunked_genesis_download/cli.py
tendermint_chunked_genesis_download/download_genesis.py
tendermint_chunked_genesis_download-1.0.16.dist-info/LICENSE
tendermint_chunked_genesis_download-1.0.16.dist-info/METADATA
tendermint_chunked_genesis_download-1.0.16.dist-info/WHEEL
tendermint_chunked_genesis_download-1.0.16.dist-info/entry_points.txt
tendermint_chunked_genesis_download-1.0.16.dist-info/top_level.txt
tendermint_chunked_genesis_download-1.0.16.dist-info/RECORD
