Metadata-Version: 2.1
Name: tendermint-chunked-genesis-download
Version: 1.0.16
Summary: Package for easily downloading a chunked Tendermint genesis from a RCP enabled node.
Home-page: https://github.com/dclaudiud/tendermint-chunked-genesis-download
Author: dclaudiud
Author-email: dclaudiud@proton.me
License: MIT
License-File: LICENSE
Requires-Dist: requests (==2.26.0)
Requires-Dist: click (==7.1.2)
Requires-Dist: setuptools (==44.1.1)
